smart_commit/__init__.py
smart_commit/cli.py
smart_commit/config.py
auto_smart_commit-0.1.0.dist-info/METADATA
auto_smart_commit-0.1.0.dist-info/WHEEL
auto_smart_commit-0.1.0.dist-info/entry_points.txt
auto_smart_commit-0.1.0.dist-info/RECORD
