Metadata-Version: 2.3
Name: auto-smart-commit
Version: 0.1.0
Summary: 
Author: SilverPeak2299
Author-email: dannydickerson03@gmail.com
Requires-Python: >=3.12
Classifier: Programming Language :: Python :: 3
Classifier: Programming Language :: Python :: 3.12
Classifier: Programming Language :: Python :: 3.13
Requires-Dist: click (>=8.2.1,<9.0.0)
Requires-Dist: google-genai (>=1.16.1,<2.0.0)
Requires-Dist: keyring (>=25.6.0,<26.0.0)
